cherryservers_sdk_python/__init__.py
cherryservers_sdk_python/_base.py
cherryservers_sdk_python/_client.py
cherryservers_sdk_python/_resource_polling.py
cherryservers_sdk_python/_version.py
cherryservers_sdk_python/backup_storages.py
cherryservers_sdk_python/block_storages.py
cherryservers_sdk_python/facade.py
cherryservers_sdk_python/images.py
cherryservers_sdk_python/ips.py
cherryservers_sdk_python/plans.py
cherryservers_sdk_python/projects.py
cherryservers_sdk_python/py.typed
cherryservers_sdk_python/regions.py
cherryservers_sdk_python/servers.py
cherryservers_sdk_python/sshkeys.py
cherryservers_sdk_python/teams.py
cherryservers_sdk_python/users.py
cherryservers_sdk_python-1.1.0.dist-info/LICENSE
cherryservers_sdk_python-1.1.0.dist-info/METADATA
cherryservers_sdk_python-1.1.0.dist-info/WHEEL
cherryservers_sdk_python-1.1.0.dist-info/RECORD
