Metadata-Version: 2.3
Name: cherryservers-sdk-python
Version: 1.1.0
Summary: The official SDK for interacting with the Cherry Servers API
License: GPL-3.0-or-later
Keywords: cherry-servers,api,client
Author: Cherry Servers
Author-email: support@cherryservers.com
Requires-Python: >=3.10,<4.0.0
Classifier: Development Status :: 5 - Production/Stable
Classifier: Topic :: Software Development :: Libraries :: Python Modules
Classifier: Intended Audience :: Developers
Classifier: Programming Language :: Python :: 3.10
Classifier: Programming Language :: Python :: 3.11
Classifier: Programming Language :: Python :: 3.12
Classifier: Programming Language :: Python :: 3.13
Requires-Dist: pydantic (>=2.10.4,<3.0.0)
Requires-Dist: requests (>=2.32.3,<3.0.0)
Project-URL: Changelog, https://github.com/cherryservers/cherryservers-sdk-python/blob/main/CHANGELOG.md
Project-URL: Documentation, https://cherryservers-sdk-python.readthedocs.io/en/latest/
Project-URL: Homepage, https://github.com/cherryservers/cherryservers-sdk-python
Project-URL: Repository, https://github.com/cherryservers/cherryservers-sdk-python
